{"hierarchy":{"name":"happy_subject_anim","children":[{"name":"base1"},{"name":"base2"},{"name":"base3"},{"name":"base4"},{"name":"base5"},{"name":"base6"},{"name":"base7"},{"name":"base8"},{"name":"base9"},{"name":"base10"},{"name":"base11"},{"name":"base12"},{"name":"base13"},{"name":"base14"},{"name":"base15"},{"name":"base16"},{"name":"base17"},{"name":"base18"},{"name":"base19"},{"name":"base20"},{"name":"base21"},{"name":"base22"},{"name":"base23"},{"name":"base24"},{"name":"base25"}],"animations":["happy_subject"]},"properties":{"base1":{"file":"exp_star.png","image":"SIMPLE","position":{"x":0,"y":0},"scale":{"x":0,"y":0},"type":"sprite"},"base2":{"file":"exp_star.png","image":"SIMPLE","position":{"x":0,"y":0},"scale":{"x":0,"y":0},"type":"sprite"},"base3":{"file":"exp_star.png","image":"SIMPLE","position":{"x":0,"y":0},"scale":{"x":0,"y":0},"type":"sprite"},"base4":{"file":"exp_star.png","image":"SIMPLE","position":{"x":0,"y":0},"scale":{"x":0,"y":0},"type":"sprite"},"base5":{"file":"exp_star.png","image":"SIMPLE","position":{"x":0,"y":0},"scale":{"x":0,"y":0},"type":"sprite"},"base6":{"file":"exp_star.png","image":"SIMPLE","position":{"x":0,"y":0},"scale":{"x":0,"y":0},"type":"sprite"},"base7":{"file":"exp_star.png","image":"SIMPLE","position":{"x":0,"y":0},"scale":{"x":0,"y":0},"type":"sprite"},"base8":{"file":"exp_point1.png","image":"SIMPLE","position":{"x":0,"y":0},"scale":{"x":0,"y":0},"type":"sprite"},"base9":{"file":"exp_point1.png","image":"SIMPLE","position":{"x":0,"y":0},"scale":{"x":0,"y":0},"type":"sprite"},"base10":{"file":"exp_point1.png","image":"SIMPLE","position":{"x":0,"y":0},"scale":{"x":0,"y":0},"type":"sprite"},"base11":{"file":"exp_point1.png","image":"SIMPLE","position":{"x":0,"y":0},"scale":{"x":0,"y":0},"type":"sprite"},"base12":{"file":"exp_point1.png","image":"SIMPLE","position":{"x":0,"y":0},"scale":{"x":0,"y":0},"type":"sprite"},"base13":{"file":"exp_point1.png","image":"SIMPLE","position":{"x":0,"y":0},"scale":{"x":0,"y":0},"type":"sprite"},"base14":{"file":"exp_point1.png","image":"SIMPLE","position":{"x":0,"y":0},"scale":{"x":0,"y":0},"type":"sprite"},"base15":{"file":"exp_point1.png","image":"SIMPLE","position":{"x":0,"y":0},"scale":{"x":0,"y":0},"type":"sprite"},"base16":{"file":"exp_point1.png","image":"SIMPLE","position":{"x":0,"y":0},"scale":{"x":0,"y":0},"type":"sprite"},"base17":{"file":"exp_point1.png","image":"SIMPLE","position":{"x":0,"y":0},"scale":{"x":0,"y":0},"type":"sprite"},"base18":{"file":"exp_point2.png","image":"SIMPLE","position":{"x":0,"y":0},"scale":{"x":0,"y":0},"type":"sprite"},"base19":{"file":"exp_point2.png","image":"SIMPLE","position":{"x":0,"y":0},"scale":{"x":0,"y":0},"type":"sprite"},"base20":{"file":"exp_point2.png","image":"SIMPLE","position":{"x":0,"y":0},"scale":{"x":0,"y":0},"type":"sprite"},"base21":{"file":"exp_point2.png","image":"SIMPLE","position":{"x":0,"y":0},"scale":{"x":0,"y":0},"type":"sprite"},"base22":{"file":"exp_point2.png","image":"SIMPLE","position":{"x":0,"y":0},"scale":{"x":0,"y":0},"type":"sprite"},"base23":{"file":"exp_point2.png","image":"SIMPLE","position":{"x":0,"y":0},"scale":{"x":0,"y":0},"type":"sprite"},"base24":{"file":"exp_point2.png","image":"SIMPLE","position":{"x":0,"y":0},"scale":{"x":0,"y":0},"type":"sprite"},"base25":{"file":"exp_point2.png","image":"SIMPLE","position":{"x":0,"y":0},"scale":{"x":0,"y":0},"type":"sprite"}}}