{"name":"subject9_happy","speed":1,"mode":"normal","data":{"leg_r1":{"position":[{"frame":0,"value":[6.1,-2.6]},{"frame":100,"value":[6.2,-2.1]},{"frame":267,"value":[5.8,-10.9]},{"frame":400,"value":[6.1,-2.6]},{"frame":583,"value":[6.1,-2.6]},{"frame":750,"value":[6.1,-2.6]}],"scaleX":[{"frame":0,"value":1}],"scaleY":[{"frame":0,"value":1}],"angle":[{"frame":0,"value":-4},{"frame":100,"value":-20},{"frame":267,"value":-20},{"frame":400,"value":-21},{"frame":583,"value":-4},{"frame":750,"value":-4}]},"leg_r1/leg_r2":{"position":[{"frame":0,"value":[-0.5,6.3]},{"frame":100,"value":[-0.5,6.3]},{"frame":267,"value":[-0.55,5.76]},{"frame":400,"value":[-0.5,6.3]},{"frame":583,"value":[-0.5,6.3]},{"frame":750,"value":[-0.5,6.3]}],"scaleX":[{"frame":0,"value":1}],"scaleY":[{"frame":0,"value":1}],"angle":[{"frame":0,"value":0},{"frame":100,"value":23},{"frame":267,"value":1},{"frame":400,"value":22},{"frame":583,"value":0},{"frame":750,"value":0}]},"leg_l1":{"position":[{"frame":0,"value":[-7.8,-2]},{"frame":100,"value":[-7.8,-2]},{"frame":267,"value":[-10.2,-8.4]},{"frame":400,"value":[-7.8,-2]},{"frame":583,"value":[-7.8,-2]},{"frame":750,"value":[-7.8,-2]}],"scaleX":[{"frame":0,"value":1}],"scaleY":[{"frame":0,"value":1}],"angle":[{"frame":0,"value":-3},{"frame":100,"value":-19},{"frame":267,"value":3},{"frame":400,"value":-26},{"frame":583,"value":-3},{"frame":750,"value":-3}]},"leg_l1/leg_l2":{"position":[{"frame":0,"value":[-0.5,6.3]},{"frame":100,"value":[-0.5,6.3]},{"frame":267,"value":[-0.52,5.46]},{"frame":400,"value":[-0.5,6.3]},{"frame":583,"value":[-0.5,6.3]},{"frame":750,"value":[-0.5,6.3]}],"scaleX":[{"frame":0,"value":1}],"scaleY":[{"frame":0,"value":1}],"angle":[{"frame":0,"value":0},{"frame":100,"value":27},{"frame":267,"value":-2},{"frame":400,"value":31},{"frame":583,"value":0},{"frame":750,"value":0}]},"base":{"position":[{"frame":0,"value":[-1.9,0.1]},{"frame":100,"value":[-1.8,3.6]},{"frame":267,"value":[-3.7,-8.8]},{"frame":400,"value":[-2.6,2.8]},{"frame":583,"value":[-1.9,0.1]},{"frame":750,"value":[-1.9,0.1]}],"scaleY":[{"frame":0,"value":1}],"scaleX":[{"frame":0,"value":1}],"angle":[{"frame":0,"value":-2},{"frame":100,"value":10},{"frame":267,"value":-7},{"frame":400,"value":8},{"frame":583,"value":-2},{"frame":750,"value":-2},{"frame":883,"value":8},{"frame":1000,"value":-7},{"frame":1333,"value":-11},{"frame":1450,"value":-2},{"frame":1833,"value":-2}]},"base/arm_l1":{"position":[{"frame":0,"value":[-5.1,-31.6]}],"scaleX":[{"frame":0,"value":1}],"scaleY":[{"frame":0,"value":1}],"angle":[{"frame":0,"value":208}]},"base/arm_l1/arm_l2":{"position":[{"frame":0,"value":[-0.7,-20.44]},{"frame":400,"value":[-0.7,-20.44]},{"frame":583,"value":[1.29,-20.31]},{"frame":750,"value":[1.29,-20.31]}],"scaleX":[{"frame":0,"value":1}],"scaleY":[{"frame":0,"value":1}],"angle":[{"frame":0,"value":-6},{"frame":100,"value":-58},{"frame":267,"value":-17},{"frame":400,"value":-24},{"frame":583,"value":80},{"frame":750,"value":80}]},"base/arm_r1":{"position":[{"frame":0,"value":[10.9,-33.8]},{"frame":750,"value":[10.9,-33.8]}],"scaleX":[{"frame":0,"value":1},{"frame":750,"value":1}],"scaleY":[{"frame":0,"value":1},{"frame":750,"value":1}],"angle":[{"frame":0,"value":164},{"frame":750,"value":164},{"frame":883,"value":140},{"frame":1000,"value":130},{"frame":1333,"value":132},{"frame":1450,"value":174}]},"base/arm_r1/arm_r2":{"position":[{"frame":0,"value":[-0.7,-20.44]},{"frame":400,"value":[-0.7,-20.44]},{"frame":583,"value":[-0.9,-19.39]},{"frame":750,"value":[-0.9,-19.39]}],"scaleX":[{"frame":0,"value":1}],"scaleY":[{"frame":0,"value":1}],"angle":[{"frame":0,"value":0},{"frame":100,"value":-105},{"frame":267,"value":-9},{"frame":400,"value":2},{"frame":583,"value":-80},{"frame":750,"value":-80},{"frame":883,"value":-108},{"frame":1000,"value":1},{"frame":1333,"value":1},{"frame":1450,"value":-80}]},"base/body":{"position":[{"frame":0,"value":[0,0]},{"frame":750,"value":[0,0]}],"scaleX":[{"frame":0,"value":1}],"scaleY":[{"frame":0,"value":1}],"angle":[{"frame":0,"value":0},{"frame":750,"value":0}]},"base/body/head":{"position":[{"frame":0,"value":[1.6,-30.5]}],"scaleX":[{"frame":0,"value":1}],"scaleY":[{"frame":0,"value":1}],"angle":[{"frame":0,"value":6},{"frame":100,"value":17},{"frame":267,"value":-5},{"frame":400,"value":12},{"frame":583,"value":-5},{"frame":750,"value":-5},{"frame":883,"value":7},{"frame":1000,"value":-8},{"frame":1333,"value":-10},{"frame":1450,"value":-5}]},"base/body/head/eyes":{"position":[{"frame":0,"value":[5.3,-20.7]}],"frameName":[{"frame":0,"value":"pi_eyes_base.png"},{"frame":100,"value":"pi_eyes_2.png"},{"frame":283,"value":"pi_eyes_base.png"},{"frame":883,"value":"pi_eyes_2.png"},{"frame":1400,"value":"pi_eyes_base.png"}]},"base/body/head/eyes/eye_l":{"position":[{"frame":0,"value":[-15.4,6.6]},{"frame":100,"value":[-12.9,2]},{"frame":283,"value":[-12.8,4]},{"frame":883,"value":[-12.8,4]}],"alpha":[{"frame":0,"value":1},{"frame":83,"value":1},{"frame":100,"value":0},{"frame":267,"value":0},{"frame":283,"value":1},{"frame":867,"value":1},{"frame":883,"value":0},{"frame":1383,"value":0},{"frame":1400,"value":1}],"frameName":[{"frame":0,"value":"pi_eye_in.png"}]},"base/body/head/eyes/eye_r":{"position":[{"frame":0,"value":[20.6,5]},{"frame":100,"value":[23,0.2]},{"frame":283,"value":[25.5,3.6]}],"alpha":[{"frame":0,"value":1},{"frame":83,"value":1},{"frame":100,"value":0},{"frame":267,"value":0},{"frame":283,"value":1},{"frame":867,"value":1},{"frame":883,"value":0},{"frame":1383,"value":0},{"frame":1400,"value":1}],"frameName":[{"frame":0,"value":"pi_eye_in.png"}]},"base/body/head/mouth":{"frameName":[{"frame":0,"value":"pi_mouth3.png"},{"frame":283,"value":"pi_mouth2.png"},{"frame":883,"value":"pi_mouth1.png"},{"frame":1317,"value":"pi_mouth2.png"}]},"base/body/head/eyebrown":{"frameName":[{"frame":0,"value":"pi_eyesbrown2.png"},{"frame":100,"value":"pi_eyesbrown1.png"}]}}}