{
	"gameTitle": {
		"en": "Rainbow Rage",
        "es": "",
        "de": "",
        "pt": "",
        "hu": "",
        "ro": "",
        "pl": "",
        "bg": "",
        "ru": "",
        "nl": "",
        "cs": "",
        "no": "",
        "sv": "",
        "da": "",
        "ar": "",
        "tr": "",
        "fr": "",
        "it": "",
        "es-419": "",
        "pt-br": ""
    },
	"shuffling": {
		"en": "SHUFFLING",
        "es": "",
        "de": "",
        "pt": "",
        "hu": "",
        "ro": "",
        "pl": "",
        "bg": "",
        "ru": "",
        "nl": "",
        "cs": "",
        "no": "",
        "sv": "",
        "da": "",
        "ar": "",
        "tr": "",
        "fr": "",
        "it": "",
        "es-419": "",
        "pt-br": ""
    },
	"paused": {
		"en": "PAUSED",
        "es": "",
        "de": "",
        "pt": "",
        "hu": "",
        "ro": "",
        "pl": "",
        "bg": "",
        "ru": "",
        "nl": "",
        "cs": "",
        "no": "",
        "sv": "",
        "da": "",
        "ar": "",
        "tr": "",
        "fr": "",
        "it": "",
        "es-419": "",
        "pt-br": ""
    },
	"levelComplete0": {
		"en": "LEVEL",
        "es": "",
        "de": "",
        "pt": "",
        "hu": "",
        "ro": "",
        "pl": "",
        "bg": "",
        "ru": "",
        "nl": "",
        "cs": "",
        "no": "",
        "sv": "",
        "da": "",
        "ar": "",
        "tr": "",
        "fr": "",
        "it": "",
        "es-419": "",
        "pt-br": ""
    },
    "levelComplete1": {
		"en": "COMPLETE!",
        "es": "",
        "de": "",
        "pt": "",
        "hu": "",
        "ro": "",
        "pl": "",
        "bg": "",
        "ru": "",
        "nl": "",
        "cs": "",
        "no": "",
        "sv": "",
        "da": "",
        "ar": "",
        "tr": "",
        "fr": "",
        "it": "",
        "es-419": "",
        "pt-br": ""
    },
	"levelFailed0": {
		"en": "OH NO!",
        "es": "",
        "de": "",
        "pt": "",
        "hu": "",
        "ro": "",
        "pl": "",
        "bg": "",
        "ru": "",
        "nl": "",
        "cs": "",
        "no": "",
        "sv": "",
        "da": "",
        "ar": "",
        "tr": "",
        "fr": "",
        "it": "",
        "es-419": "",
        "pt-br": ""
    },
    "levelFailed1": {
		"en": "TRY AGAIN",
        "es": "",
        "de": "",
        "pt": "",
        "hu": "",
        "ro": "",
        "pl": "",
        "bg": "",
        "ru": "",
        "nl": "",
        "cs": "",
        "no": "",
        "sv": "",
        "da": "",
        "ar": "",
        "tr": "",
        "fr": "",
        "it": "",
        "es-419": "",
        "pt-br": ""
    },
	"help0": {
		"en": "Swipe to match icons",
        "es": "",
        "de": "",
        "pt": "",
        "hu": "",
        "ro": "",
        "pl": "",
        "bg": "",
        "ru": "",
        "nl": "",
        "cs": "",
        "no": "",
        "sv": "",
        "da": "",
        "ar": "",
        "tr": "",
        "fr": "",
        "it": "",
        "es-419": "",
        "pt-br": ""
    },
	"help1": {
		"en": "Tap to launch friend's attack",
        "es": "",
        "de": "",
        "pt": "",
        "hu": "",
        "ro": "",
        "pl": "",
        "bg": "",
        "ru": "",
        "nl": "",
        "cs": "",
        "no": "",
        "sv": "",
        "da": "",
        "ar": "",
        "tr": "",
        "fr": "",
        "it": "",
        "es-419": "",
        "pt-br": ""
    },
	"unlockFriend0": {
		"en": "Dr. Fox unlocked!",
        "es": "",
        "de": "",
        "pt": "",
        "hu": "",
        "ro": "",
        "pl": "",
        "bg": "",
        "ru": "",
        "nl": "",
        "cs": "",
        "no": "",
        "sv": "",
        "da": "",
        "ar": "",
        "tr": "",
        "fr": "",
        "it": "",
        "es-419": "",
        "pt-br": ""
    },
	"unlockFriend1": {
		"en": "Puppycorn unlocked!",
        "es": "",
        "de": "",
        "pt": "",
        "hu": "",
        "ro": "",
        "pl": "",
        "bg": "",
        "ru": "",
        "nl": "",
        "cs": "",
        "no": "",
        "sv": "",
        "da": "",
        "ar": "",
        "tr": "",
        "fr": "",
        "it": "",
        "es-419": "",
        "pt-br": ""
    },
	"unlockFriend2": {
		"en": "Hawkodile unlocked!",
        "es": "",
        "de": "",
        "pt": "",
        "hu": "",
        "ro": "",
        "pl": "",
        "bg": "",
        "ru": "",
        "nl": "",
        "cs": "",
        "no": "",
        "sv": "",
        "da": "",
        "ar": "",
        "tr": "",
        "fr": "",
        "it": "",
        "es-419": "",
        "pt-br": ""
    },
	"unlockFriend3": {
		"en": "Richard unlocked!",
        "es": "",
        "de": "",
        "pt": "",
        "hu": "",
        "ro": "",
        "pl": "",
        "bg": "",
        "ru": "",
        "nl": "",
        "cs": "",
        "no": "",
        "sv": "",
        "da": "",
        "ar": "",
        "tr": "",
        "fr": "",
        "it": "",
        "es-419": "",
        "pt-br": ""
    },
	"unlockEnemy0": {
		"en": "Master Frown unlocked!",
        "es": "",
        "de": "",
        "pt": "",
        "hu": "",
        "ro": "",
        "pl": "",
        "bg": "",
        "ru": "",
        "nl": "",
        "cs": "",
        "no": "",
        "sv": "",
        "da": "",
        "ar": "",
        "tr": "",
        "fr": "",
        "it": "",
        "es-419": "",
        "pt-br": ""
    },
	"unlockEnemy1": {
		"en": "Master Hazard unlocked!",
        "es": "",
        "de": "",
        "pt": "",
        "hu": "",
        "ro": "",
        "pl": "",
        "bg": "",
        "ru": "",
        "nl": "",
        "cs": "",
        "no": "",
        "sv": "",
        "da": "",
        "ar": "",
        "tr": "",
        "fr": "",
        "it": "",
        "es-419": "",
        "pt-br": ""
    },
	"unlockEnemy2": {
		"en": "Master Malice unlocked!",
        "es": "",
        "de": "",
        "pt": "",
        "hu": "",
        "ro": "",
        "pl": "",
        "bg": "",
        "ru": "",
        "nl": "",
        "cs": "",
        "no": "",
        "sv": "",
        "da": "",
        "ar": "",
        "tr": "",
        "fr": "",
        "it": "",
        "es-419": "",
        "pt-br": ""
    },
	"unlockEnemy3": {
		"en": "Master Pain unlocked!",
        "es": "",
        "de": "",
        "pt": "",
        "hu": "",
        "ro": "",
        "pl": "",
        "bg": "",
        "ru": "",
        "nl": "",
        "cs": "",
        "no": "",
        "sv": "",
        "da": "",
        "ar": "",
        "tr": "",
        "fr": "",
        "it": "",
        "es-419": "",
        "pt-br": ""
    },
	"unlockEnemy4": {
		"en": "Master Fear unlocked!",
        "es": "",
        "de": "",
        "pt": "",
        "hu": "",
        "ro": "",
        "pl": "",
        "bg": "",
        "ru": "",
        "nl": "",
        "cs": "",
        "no": "",
        "sv": "",
        "da": "",
        "ar": "",
        "tr": "",
        "fr": "",
        "it": "",
        "es-419": "",
        "pt-br": ""
    },
	"upgradeHero": {
		"en": "Unikitty upgraded!",
        "es": "",
        "de": "",
        "pt": "",
        "hu": "",
        "ro": "",
        "pl": "",
        "bg": "",
        "ru": "",
        "nl": "",
        "cs": "",
        "no": "",
        "sv": "",
        "da": "",
        "ar": "",
        "tr": "",
        "fr": "",
        "it": "",
        "es-419": "",
        "pt-br": ""
    },
	"upgradeFriend0": {
		"en": "Dr. Fox upgraded!",
        "es": "",
        "de": "",
        "pt": "",
        "hu": "",
        "ro": "",
        "pl": "",
        "bg": "",
        "ru": "",
        "nl": "",
        "cs": "",
        "no": "",
        "sv": "",
        "da": "",
        "ar": "",
        "tr": "",
        "fr": "",
        "it": "",
        "es-419": "",
        "pt-br": ""
    },
	"upgradeFriend1": {
		"en": "Puppycorn upgraded!",
        "es": "",
        "de": "",
        "pt": "",
        "hu": "",
        "ro": "",
        "pl": "",
        "bg": "",
        "ru": "",
        "nl": "",
        "cs": "",
        "no": "",
        "sv": "",
        "da": "",
        "ar": "",
        "tr": "",
        "fr": "",
        "it": "",
        "es-419": "",
        "pt-br": ""
    },
	"upgradeFriend2": {
		"en": "Hawkodile upgraded!",
        "es": "",
        "de": "",
        "pt": "",
        "hu": "",
        "ro": "",
        "pl": "",
        "bg": "",
        "ru": "",
        "nl": "",
        "cs": "",
        "no": "",
        "sv": "",
        "da": "",
        "ar": "",
        "tr": "",
        "fr": "",
        "it": "",
        "es-419": "",
        "pt-br": ""
    },
	"upgradeFriend3": {
		"en": "Richard upgraded!",
        "es": "",
        "de": "",
        "pt": "",
        "hu": "",
        "ro": "",
        "pl": "",
        "bg": "",
        "ru": "",
        "nl": "",
        "cs": "",
        "no": "",
        "sv": "",
        "da": "",
        "ar": "",
        "tr": "",
        "fr": "",
        "it": "",
        "es-419": "",
        "pt-br": ""
    },
	"congratulations": {
		"en": "Congratulations",
        "es": "",
        "de": "",
        "pt": "",
        "hu": "",
        "ro": "",
        "pl": "",
        "bg": "",
        "ru": "",
        "nl": "",
        "cs": "",
        "no": "",
        "sv": "",
        "da": "",
        "ar": "",
        "tr": "",
        "fr": "",
        "it": "",
        "es-419": "",
        "pt-br": ""
    },
    "tutorial0": {
        "en": "Aargh! The Doom Lords are attacking!",
        "es": "",
        "de": "",
        "pt": "",
        "hu": "",
        "ro": "",
        "pl": "",
        "bg": "",
        "ru": "",
        "nl": "",
        "cs": "",
        "no": "",
        "sv": "",
        "da": "",
        "ar": "",
        "tr": "",
        "fr": "",
        "it": "",
        "es-419": "",
        "pt-br": ""
    },
    "tutorial1": {
        "en": "Swap tiles to match icons.",
        "es": "",
        "de": "",
        "pt": "",
        "hu": "",
        "ro": "",
        "pl": "",
        "bg": "",
        "ru": "",
        "nl": "",
        "cs": "",
        "no": "",
        "sv": "",
        "da": "",
        "ar": "",
        "tr": "",
        "fr": "",
        "it": "",
        "es-419": "",
        "pt-br": ""
    },
    "tutorial2": {
        "en": "Match icons to power up Unikitty and her friends.",
        "es": "",
        "de": "",
        "pt": "",
        "hu": "",
        "ro": "",
        "pl": "",
        "bg": "",
        "ru": "",
        "nl": "",
        "cs": "",
        "no": "",
        "sv": "",
        "da": "",
        "ar": "",
        "tr": "",
        "fr": "",
        "it": "",
        "es-419": "",
        "pt-br": ""
    },
    "tutorial3": {
        "en": "Tap on powered-up friends to launch an attack!",
        "es": "",
        "de": "",
        "pt": "",
        "hu": "",
        "ro": "",
        "pl": "",
        "bg": "",
        "ru": "",
        "nl": "",
        "cs": "",
        "no": "",
        "sv": "",
        "da": "",
        "ar": "",
        "tr": "",
        "fr": "",
        "it": "",
        "es-419": "",
        "pt-br": ""
    },
    "tutorial4": {
        "en": "Power up Unikitty to trigger Rage Mode!",
        "es": "",
        "de": "",
        "pt": "",
        "hu": "",
        "ro": "",
        "pl": "",
        "bg": "",
        "ru": "",
        "nl": "",
        "cs": "",
        "no": "",
        "sv": "",
        "da": "",
        "ar": "",
        "tr": "",
        "fr": "",
        "it": "",
        "es-419": "",
        "pt-br": ""
    },
    "tutorial5": {
        "en": "Match 4 icons to create a star burst or pizza boost",
        "es": "",
        "de": "",
        "pt": "",
        "hu": "",
        "ro": "",
        "pl": "",
        "bg": "",
        "ru": "",
        "nl": "",
        "cs": "",
        "no": "",
        "sv": "",
        "da": "",
        "ar": "",
        "tr": "",
        "fr": "",
        "it": "",
        "es-419": "",
        "pt-br": ""
    },
    "tutorial6": {
        "en": "Use the boost now!",
        "es": "",
        "de": "",
        "pt": "",
        "hu": "",
        "ro": "",
        "pl": "",
        "bg": "",
        "ru": "",
        "nl": "",
        "cs": "",
        "no": "",
        "sv": "",
        "da": "",
        "ar": "",
        "tr": "",
        "fr": "",
        "it": "",
        "es-419": "",
        "pt-br": ""
    },
    "tutorial7": {
        "en": "Match 5 icons to create a rainbow!",
        "es": "",
        "de": "",
        "pt": "",
        "hu": "",
        "ro": "",
        "pl": "",
        "bg": "",
        "ru": "",
        "nl": "",
        "cs": "",
        "no": "",
        "sv": "",
        "da": "",
        "ar": "",
        "tr": "",
        "fr": "",
        "it": "",
        "es-419": "",
        "pt-br": ""
    },
    "tutorial8": {
        "en": "Use the boost now!",
        "es": "",
        "de": "",
        "pt": "",
        "hu": "",
        "ro": "",
        "pl": "",
        "bg": "",
        "ru": "",
        "nl": "",
        "cs": "",
        "no": "",
        "sv": "",
        "da": "",
        "ar": "",
        "tr": "",
        "fr": "",
        "it": "",
        "es-419": "",
        "pt-br": ""
    }
}