{
	"alpha": {
		"start": 0.07,
		"end": 0.06
	},
	"scale": {
		"start": 2,
		"end": 0.5,
		"minimumScaleMultiplier": 2
	},
	"color": {
		"start": "#ffffff",
		"end": "#c7ecff"
	},
	"speed": {
		"start": 0,
		"end": 0,
		"minimumSpeedMultiplier": 0.001
	},
	"acceleration": {
		"x": 0,
		"y": 0
	},
	"maxSpeed": 0,
	"startRotation": {
		"min": 0,
		"max": 0
	},
	"noRotation": false,
	"rotationSpeed": {
		"min": 0,
		"max": 0
	},
	"lifetime": {
		"min": 0.001,
		"max": 0.8
	},
	"blendMode": "normal",
	"frequency": 0.001,
	"emitterLifetime": -1,
	"maxParticles": 500,
	"pos": {
		"x": 0,
		"y": 0
	},
	"addAtBack": false,
	"spawnType": "rect",
	"spawnRect": {
		"x": 0,
		"y": 0,
		"w": 0,
		"h": 0
	}
}