{"frames":[{"filename":"1x1.png","frame":{"x":338,"y":84,"w":1,"h":1},"rotated":false,"trimmed":false,"spriteSourceSize":{"x":0,"y":0,"w":1,"h":1},"sourceSize":{"w":1,"h":1}},{"filename":"bg_conteiner.png","frame":{"x":2,"y":2,"w":812,"h":69},"rotated":false,"trimmed":true,"spriteSourceSize":{"x":0,"y":0,"w":812,"h":69},"sourceSize":{"w":818,"h":69}},{"filename":"lemmings_container.png","frame":{"x":865,"y":29,"w":47,"h":51},"rotated":false,"trimmed":true,"spriteSourceSize":{"x":1,"y":5,"w":47,"h":51},"sourceSize":{"w":48,"h":57}},{"filename":"pause.png","frame":{"x":914,"y":29,"w":32,"h":37},"rotated":false,"trimmed":true,"spriteSourceSize":{"x":3,"y":2,"w":32,"h":37},"sourceSize":{"w":36,"h":39}},{"filename":"star.png","frame":{"x":948,"y":29,"w":25,"h":26},"rotated":false,"trimmed":true,"spriteSourceSize":{"x":0,"y":0,"w":25,"h":26},"sourceSize":{"w":26,"h":28}},{"filename":"timebar_0.png","frame":{"x":816,"y":29,"w":47,"h":53},"rotated":false,"trimmed":true,"spriteSourceSize":{"x":3,"y":1,"w":47,"h":53},"sourceSize":{"w":50,"h":54}},{"filename":"timebar_1.png","frame":{"x":816,"y":2,"w":179,"h":25},"rotated":false,"trimmed":true,"spriteSourceSize":{"x":3,"y":4,"w":179,"h":25},"sourceSize":{"w":183,"h":30}},{"filename":"timebar_2.png","frame":{"x":2,"y":73,"w":166,"h":12},"rotated":false,"trimmed":true,"spriteSourceSize":{"x":3,"y":2,"w":166,"h":12},"sourceSize":{"w":171,"h":16}},{"filename":"timebar_3.png","frame":{"x":170,"y":73,"w":166,"h":12},"rotated":false,"trimmed":true,"spriteSourceSize":{"x":3,"y":2,"w":166,"h":12},"sourceSize":{"w":171,"h":16}}],"meta":{"app":"http://www.codeandweb.com/texturepacker","version":"1.0","image":"ui_gameplay_lemming.png","format":"RGBA8888","size":{"w":997,"h":87},"scale":"1","smartupdate":"$TexturePacker:SmartUpdate:8958da99c14fc91a51227e16a110c0c8:afd78f9bd7cc8ec7a4e8debc21611592:a7bef07df1e2c135d86fbc8fe7c099e9$"}}