<level width="13" height="22" size="40" star1="10" star2="15" star3="20" total="30">
  <normal type="7x2" posx="0" posy="0" group="0" rotate="0" dirx="0" diry="0" width="0" height="0" timer="0"/>
  <normal type="0x2" posx="0" posy="1" group="0" rotate="0" dirx="0" diry="0" width="0" height="0" timer="0"/>
  <normal type="0x2" posx="0" posy="2" group="0" rotate="0" dirx="0" diry="0" width="0" height="0" timer="0"/>
  <normal type="0x2" posx="0" posy="3" group="0" rotate="0" dirx="0" diry="0" width="0" height="0" timer="0"/>
  <normal type="0x2" posx="0" posy="4" group="0" rotate="0" dirx="0" diry="0" width="0" height="0" timer="0"/>
  <normal type="0x2" posx="0" posy="5" group="0" rotate="0" dirx="0" diry="0" width="0" height="0" timer="0"/>
  <normal type="0x2" posx="0" posy="6" group="0" rotate="0" dirx="0" diry="0" width="0" height="0" timer="0"/>
  <normal type="0x2" posx="0" posy="7" group="0" rotate="0" dirx="0" diry="0" width="0" height="0" timer="0"/>
  <normal type="0x2" posx="0" posy="8" group="0" rotate="0" dirx="0" diry="0" width="0" height="0" timer="0"/>
  <normal type="0x2" posx="0" posy="9" group="0" rotate="0" dirx="0" diry="0" width="0" height="0" timer="0"/>
  <normal type="1x2" posx="0" posy="10" group="0" rotate="0" dirx="0" diry="0" width="0" height="0" timer="0"/>
  <normal type="7x2" posx="0" posy="11" group="0" rotate="0" dirx="0" diry="0" width="0" height="0" timer="0"/>
  <normal type="0x2" posx="0" posy="12" group="0" rotate="0" dirx="0" diry="0" width="0" height="0" timer="0"/>
  <normal type="0x2" posx="0" posy="13" group="0" rotate="0" dirx="0" diry="0" width="0" height="0" timer="0"/>
  <normal type="0x2" posx="0" posy="14" group="0" rotate="0" dirx="0" diry="0" width="0" height="0" timer="0"/>
  <normal type="0x2" posx="0" posy="15" group="0" rotate="0" dirx="0" diry="0" width="0" height="0" timer="0"/>
  <normal type="0x2" posx="0" posy="16" group="0" rotate="0" dirx="0" diry="0" width="0" height="0" timer="0"/>
  <normal type="0x2" posx="0" posy="17" group="0" rotate="0" dirx="0" diry="0" width="0" height="0" timer="0"/>
  <normal type="0x2" posx="0" posy="18" group="0" rotate="0" dirx="0" diry="0" width="0" height="0" timer="0"/>
  <normal type="0x2" posx="0" posy="19" group="0" rotate="0" dirx="0" diry="0" width="0" height="0" timer="0"/>
  <normal type="0x2" posx="0" posy="20" group="0" rotate="0" dirx="0" diry="0" width="0" height="0" timer="0"/>
  <normal type="1x2" posx="0" posy="21" group="0" rotate="0" dirx="0" diry="0" width="0" height="0" timer="0"/>
  <normal type="6x1" posx="1" posy="0" group="0" rotate="0" dirx="0" diry="0" width="0" height="0" timer="0"/>
  <normal type="7x1" posx="1" posy="10" group="0" rotate="0" dirx="0" diry="0" width="0" height="0" timer="0"/>
  <normal type="6x1" posx="1" posy="11" group="0" rotate="0" dirx="0" diry="0" width="0" height="0" timer="0"/>
  <normal type="7x1" posx="1" posy="21" group="0" rotate="0" dirx="0" diry="0" width="0" height="0" timer="0"/>
  <normal type="4x3" posx="2" posy="0" group="0" rotate="0" dirx="0" diry="0" width="0" height="0" timer="0"/>
  <normal type="1x1" posx="2" posy="1" group="0" rotate="0" dirx="0" diry="0" width="0" height="0" timer="0"/>
  <normal type="4x1" posx="2" posy="3" group="0" rotate="0" dirx="0" diry="0" width="0" height="0" timer="0"/>
  <normal type="1x1" posx="2" posy="4" group="0" rotate="0" dirx="0" diry="0" width="0" height="0" timer="0"/>
  <normal type="4x1" posx="2" posy="6" group="0" rotate="0" dirx="0" diry="0" width="0" height="0" timer="0"/>
  <normal type="2x1" posx="2" posy="7" group="0" rotate="0" dirx="0" diry="0" width="0" height="0" timer="0"/>
  <normal type="4x1" posx="2" posy="9" group="0" rotate="0" dirx="0" diry="0" width="0" height="0" timer="0"/>
  <normal type="2x3" posx="2" posy="10" group="0" rotate="0" dirx="0" diry="0" width="0" height="0" timer="0"/>
  <normal type="4x3" posx="2" posy="11" group="0" rotate="0" dirx="0" diry="0" width="0" height="0" timer="0"/>
  <normal type="1x1" posx="2" posy="12" group="0" rotate="0" dirx="0" diry="0" width="0" height="0" timer="0"/>
  <normal type="4x1" posx="2" posy="14" group="0" rotate="0" dirx="0" diry="0" width="0" height="0" timer="0"/>
  <normal type="1x1" posx="2" posy="15" group="0" rotate="0" dirx="0" diry="0" width="0" height="0" timer="0"/>
  <normal type="4x1" posx="2" posy="17" group="0" rotate="0" dirx="0" diry="0" width="0" height="0" timer="0"/>
  <normal type="2x1" posx="2" posy="18" group="0" rotate="0" dirx="0" diry="0" width="0" height="0" timer="0"/>
  <normal type="4x1" posx="2" posy="20" group="0" rotate="0" dirx="0" diry="0" width="0" height="0" timer="0"/>
  <normal type="2x3" posx="2" posy="21" group="0" rotate="0" dirx="0" diry="0" width="0" height="0" timer="0"/>
  <normal type="5x1" posx="3" posy="0" group="0" rotate="0" dirx="0" diry="0" width="0" height="0" timer="0"/>
  <normal type="5x1" posx="3" posy="10" group="0" rotate="0" dirx="0" diry="0" width="0" height="0" timer="0"/>
  <normal type="5x1" posx="3" posy="11" group="0" rotate="0" dirx="0" diry="0" width="0" height="0" timer="0"/>
  <normal type="5x1" posx="3" posy="21" group="0" rotate="0" dirx="0" diry="0" width="0" height="0" timer="0"/>
  <normal type="4x3" posx="4" posy="0" group="0" rotate="0" dirx="0" diry="0" width="0" height="0" timer="0"/>
  <normal type="3x1" posx="4" posy="1" group="0" rotate="0" dirx="0" diry="0" width="0" height="0" timer="0"/>
  <normal type="7x2" posx="4" posy="3" group="0" rotate="0" dirx="0" diry="0" width="0" height="0" timer="0"/>
  <normal type="1x1" posx="4" posy="4" group="0" rotate="0" dirx="0" diry="0" width="0" height="0" timer="0"/>
  <normal type="4x1" posx="4" posy="6" group="0" rotate="0" dirx="0" diry="0" width="0" height="0" timer="0"/>
  <normal type="2x2" posx="4" posy="7" group="0" rotate="0" dirx="0" diry="0" width="0" height="0" timer="0"/>
  <normal type="4x1" posx="4" posy="9" group="0" rotate="0" dirx="0" diry="0" width="0" height="0" timer="0"/>
  <normal type="1x3" posx="4" posy="10" group="0" rotate="0" dirx="0" diry="0" width="0" height="0" timer="0"/>
  <normal type="4x3" posx="4" posy="11" group="0" rotate="0" dirx="0" diry="0" width="0" height="0" timer="0"/>
  <normal type="3x1" posx="4" posy="12" group="0" rotate="0" dirx="0" diry="0" width="0" height="0" timer="0"/>
  <normal type="7x2" posx="4" posy="14" group="0" rotate="0" dirx="0" diry="0" width="0" height="0" timer="0"/>
  <normal type="1x1" posx="4" posy="15" group="0" rotate="0" dirx="0" diry="0" width="0" height="0" timer="0"/>
  <normal type="4x1" posx="4" posy="17" group="0" rotate="0" dirx="0" diry="0" width="0" height="0" timer="0"/>
  <normal type="2x2" posx="4" posy="18" group="0" rotate="0" dirx="0" diry="0" width="0" height="0" timer="0"/>
  <normal type="4x1" posx="4" posy="20" group="0" rotate="0" dirx="0" diry="0" width="0" height="0" timer="0"/>
  <normal type="1x3" posx="4" posy="21" group="0" rotate="0" dirx="0" diry="0" width="0" height="0" timer="0"/>
  <normal type="7x1" posx="5" posy="0" group="0" rotate="0" dirx="0" diry="0" width="0" height="0" timer="0"/>
  <normal type="6x0" posx="5" posy="3" group="0" rotate="0" dirx="0" diry="0" width="0" height="0" timer="0"/>
  <normal type="6x0" posx="5" posy="7" group="0" rotate="0" dirx="0" diry="0" width="0" height="0" timer="0"/>
  <normal type="6x1" posx="5" posy="10" group="0" rotate="0" dirx="0" diry="0" width="0" height="0" timer="0"/>
  <normal type="7x1" posx="5" posy="11" group="0" rotate="0" dirx="0" diry="0" width="0" height="0" timer="0"/>
  <normal type="6x0" posx="5" posy="14" group="0" rotate="0" dirx="0" diry="0" width="0" height="0" timer="0"/>
  <normal type="6x0" posx="5" posy="18" group="0" rotate="0" dirx="0" diry="0" width="0" height="0" timer="0"/>
  <normal type="6x1" posx="5" posy="21" group="0" rotate="0" dirx="0" diry="0" width="0" height="0" timer="0"/>
  <normal type="5x1" posx="6" posy="0" group="0" rotate="0" dirx="0" diry="0" width="0" height="0" timer="0"/>
  <normal type="5x1" posx="6" posy="10" group="0" rotate="0" dirx="0" diry="0" width="0" height="0" timer="0"/>
  <normal type="5x1" posx="6" posy="11" group="0" rotate="0" dirx="0" diry="0" width="0" height="0" timer="0"/>
  <normal type="5x1" posx="6" posy="21" group="0" rotate="0" dirx="0" diry="0" width="0" height="0" timer="0"/>
  <normal type="6x1" posx="7" posy="0" group="0" rotate="0" dirx="0" diry="0" width="0" height="0" timer="0"/>
  <normal type="3x0" posx="7" posy="3" group="0" rotate="0" dirx="0" diry="0" width="0" height="0" timer="0"/>
  <normal type="4x0" posx="7" posy="7" group="0" rotate="0" dirx="0" diry="0" width="0" height="0" timer="0"/>
  <normal type="7x1" posx="7" posy="10" group="0" rotate="0" dirx="0" diry="0" width="0" height="0" timer="0"/>
  <normal type="6x1" posx="7" posy="11" group="0" rotate="0" dirx="0" diry="0" width="0" height="0" timer="0"/>
  <normal type="3x0" posx="7" posy="14" group="0" rotate="0" dirx="0" diry="0" width="0" height="0" timer="0"/>
  <normal type="4x0" posx="7" posy="18" group="0" rotate="0" dirx="0" diry="0" width="0" height="0" timer="0"/>
  <normal type="7x1" posx="7" posy="21" group="0" rotate="0" dirx="0" diry="0" width="0" height="0" timer="0"/>
  <normal type="4x3" posx="8" posy="0" group="0" rotate="0" dirx="0" diry="0" width="0" height="0" timer="0"/>
  <normal type="1x1" posx="8" posy="1" group="0" rotate="0" dirx="0" diry="0" width="0" height="0" timer="0"/>
  <normal type="0x3" posx="8" posy="3" group="0" rotate="0" dirx="0" diry="0" width="0" height="0" timer="0"/>
  <normal type="2x1" posx="8" posy="4" group="0" rotate="0" dirx="0" diry="0" width="0" height="0" timer="0"/>
  <normal type="4x1" posx="8" posy="6" group="0" rotate="0" dirx="0" diry="0" width="0" height="0" timer="0"/>
  <normal type="4x2" posx="8" posy="7" group="0" rotate="0" dirx="0" diry="0" width="0" height="0" timer="0"/>
  <normal type="4x1" posx="8" posy="9" group="0" rotate="0" dirx="0" diry="0" width="0" height="0" timer="0"/>
  <normal type="1x3" posx="8" posy="10" group="0" rotate="0" dirx="0" diry="0" width="0" height="0" timer="0"/>
  <normal type="4x3" posx="8" posy="11" group="0" rotate="0" dirx="0" diry="0" width="0" height="0" timer="0"/>
  <normal type="1x1" posx="8" posy="12" group="0" rotate="0" dirx="0" diry="0" width="0" height="0" timer="0"/>
  <normal type="0x3" posx="8" posy="14" group="0" rotate="0" dirx="0" diry="0" width="0" height="0" timer="0"/>
  <normal type="2x1" posx="8" posy="15" group="0" rotate="0" dirx="0" diry="0" width="0" height="0" timer="0"/>
  <normal type="4x1" posx="8" posy="17" group="0" rotate="0" dirx="0" diry="0" width="0" height="0" timer="0"/>
  <normal type="4x2" posx="8" posy="18" group="0" rotate="0" dirx="0" diry="0" width="0" height="0" timer="0"/>
  <normal type="4x1" posx="8" posy="20" group="0" rotate="0" dirx="0" diry="0" width="0" height="0" timer="0"/>
  <normal type="1x3" posx="8" posy="21" group="0" rotate="0" dirx="0" diry="0" width="0" height="0" timer="0"/>
  <normal type="5x1" posx="9" posy="0" group="0" rotate="0" dirx="0" diry="0" width="0" height="0" timer="0"/>
  <normal type="5x1" posx="9" posy="10" group="0" rotate="0" dirx="0" diry="0" width="0" height="0" timer="0"/>
  <normal type="5x1" posx="9" posy="11" group="0" rotate="0" dirx="0" diry="0" width="0" height="0" timer="0"/>
  <normal type="5x1" posx="9" posy="21" group="0" rotate="0" dirx="0" diry="0" width="0" height="0" timer="0"/>
  <normal type="4x3" posx="10" posy="0" group="0" rotate="0" dirx="0" diry="0" width="0" height="0" timer="0"/>
  <normal type="1x1" posx="10" posy="1" group="0" rotate="0" dirx="0" diry="0" width="0" height="0" timer="0"/>
  <normal type="4x1" posx="10" posy="3" group="0" rotate="0" dirx="0" diry="0" width="0" height="0" timer="0"/>
  <normal type="1x1" posx="10" posy="4" group="0" rotate="0" dirx="0" diry="0" width="0" height="0" timer="0"/>
  <normal type="4x1" posx="10" posy="6" group="0" rotate="0" dirx="0" diry="0" width="0" height="0" timer="0"/>
  <normal type="1x1" posx="10" posy="7" group="0" rotate="0" dirx="0" diry="0" width="0" height="0" timer="0"/>
  <normal type="4x1" posx="10" posy="9" group="0" rotate="0" dirx="0" diry="0" width="0" height="0" timer="0"/>
  <normal type="3x3" posx="10" posy="10" group="0" rotate="0" dirx="0" diry="0" width="0" height="0" timer="0"/>
  <normal type="4x3" posx="10" posy="11" group="0" rotate="0" dirx="0" diry="0" width="0" height="0" timer="0"/>
  <normal type="1x1" posx="10" posy="12" group="0" rotate="0" dirx="0" diry="0" width="0" height="0" timer="0"/>
  <normal type="4x1" posx="10" posy="14" group="0" rotate="0" dirx="0" diry="0" width="0" height="0" timer="0"/>
  <normal type="1x1" posx="10" posy="15" group="0" rotate="0" dirx="0" diry="0" width="0" height="0" timer="0"/>
  <normal type="4x1" posx="10" posy="17" group="0" rotate="0" dirx="0" diry="0" width="0" height="0" timer="0"/>
  <normal type="1x1" posx="10" posy="18" group="0" rotate="0" dirx="0" diry="0" width="0" height="0" timer="0"/>
  <normal type="4x1" posx="10" posy="20" group="0" rotate="0" dirx="0" diry="0" width="0" height="0" timer="0"/>
  <normal type="3x3" posx="10" posy="21" group="0" rotate="0" dirx="0" diry="0" width="0" height="0" timer="0"/>
  <normal type="7x1" posx="11" posy="0" group="0" rotate="0" dirx="0" diry="0" width="0" height="0" timer="0"/>
  <normal type="5x1" posx="11" posy="10" group="0" rotate="0" dirx="0" diry="0" width="0" height="0" timer="0"/>
  <normal type="7x1" posx="11" posy="11" group="0" rotate="0" dirx="0" diry="0" width="0" height="0" timer="0"/>
  <normal type="5x1" posx="11" posy="21" group="0" rotate="0" dirx="0" diry="0" width="0" height="0" timer="0"/>
  <normal type="0x3" posx="12" posy="0" group="0" rotate="0" dirx="0" diry="0" width="0" height="0" timer="0"/>
  <normal type="0x2" posx="12" posy="1" group="0" rotate="0" dirx="0" diry="0" width="0" height="0" timer="0"/>
  <normal type="0x2" posx="12" posy="2" group="0" rotate="0" dirx="0" diry="0" width="0" height="0" timer="0"/>
  <normal type="0x2" posx="12" posy="3" group="0" rotate="0" dirx="0" diry="0" width="0" height="0" timer="0"/>
  <normal type="0x2" posx="12" posy="4" group="0" rotate="0" dirx="0" diry="0" width="0" height="0" timer="0"/>
  <normal type="0x2" posx="12" posy="5" group="0" rotate="0" dirx="0" diry="0" width="0" height="0" timer="0"/>
  <normal type="0x2" posx="12" posy="6" group="0" rotate="0" dirx="0" diry="0" width="0" height="0" timer="0"/>
  <normal type="0x2" posx="12" posy="7" group="0" rotate="0" dirx="0" diry="0" width="0" height="0" timer="0"/>
  <normal type="0x2" posx="12" posy="8" group="0" rotate="0" dirx="0" diry="0" width="0" height="0" timer="0"/>
  <normal type="0x2" posx="12" posy="9" group="0" rotate="0" dirx="0" diry="0" width="0" height="0" timer="0"/>
  <normal type="4x2" posx="12" posy="10" group="0" rotate="0" dirx="0" diry="0" width="0" height="0" timer="0"/>
  <normal type="0x3" posx="12" posy="11" group="0" rotate="0" dirx="0" diry="0" width="0" height="0" timer="0"/>
  <normal type="0x2" posx="12" posy="12" group="0" rotate="0" dirx="0" diry="0" width="0" height="0" timer="0"/>
  <normal type="0x2" posx="12" posy="13" group="0" rotate="0" dirx="0" diry="0" width="0" height="0" timer="0"/>
  <normal type="0x2" posx="12" posy="14" group="0" rotate="0" dirx="0" diry="0" width="0" height="0" timer="0"/>
  <normal type="0x2" posx="12" posy="15" group="0" rotate="0" dirx="0" diry="0" width="0" height="0" timer="0"/>
  <normal type="0x2" posx="12" posy="16" group="0" rotate="0" dirx="0" diry="0" width="0" height="0" timer="0"/>
  <normal type="0x2" posx="12" posy="17" group="0" rotate="0" dirx="0" diry="0" width="0" height="0" timer="0"/>
  <normal type="0x2" posx="12" posy="18" group="0" rotate="0" dirx="0" diry="0" width="0" height="0" timer="0"/>
  <normal type="0x2" posx="12" posy="19" group="0" rotate="0" dirx="0" diry="0" width="0" height="0" timer="0"/>
  <normal type="0x2" posx="12" posy="20" group="0" rotate="0" dirx="0" diry="0" width="0" height="0" timer="0"/>
  <normal type="4x2" posx="12" posy="21" group="0" rotate="0" dirx="0" diry="0" width="0" height="0" timer="0"/>
  <character type="prohyas" posx="1" posy="1" group="0" rotate="0" dirx="0" diry="0" width="0" height="0" timer="0"/>
  <character type="exit" posx="6" posy="5" group="0" rotate="0" dirx="0" diry="0" width="0" height="0" timer="0"/>
  <character type="exit" posx="6" posy="16" group="0" rotate="0" dirx="0" diry="0" width="0" height="0" timer="0"/>
  <character type="nohyas" posx="11" posy="20" group="0" rotate="0" dirx="0" diry="0" width="0" height="0" timer="0"/>
  <decoration type="f1x3" posx="1" posy="3" group="0" rotate="0" dirx="0" diry="0" width="0" height="0" timer="0"/>
  <decoration type="f0x0" posx="1" posy="9" group="0" rotate="0" dirx="0" diry="0" width="0" height="0" timer="0"/>
  <decoration type="f1x3" posx="1" posy="14" group="0" rotate="0" dirx="0" diry="0" width="0" height="0" timer="0"/>
  <decoration type="f0x0" posx="1" posy="20" group="0" rotate="0" dirx="0" diry="0" width="0" height="0" timer="0"/>
  <decoration type="f1x0" posx="3" posy="2" group="0" rotate="0" dirx="0" diry="0" width="0" height="0" timer="0"/>
  <decoration type="f1x0" posx="3" posy="13" group="0" rotate="0" dirx="0" diry="0" width="0" height="0" timer="0"/>
  <decoration type="f0x2" posx="4" posy="5" group="0" rotate="0" dirx="0" diry="0" width="0" height="0" timer="0"/>
  <decoration type="f0x2" posx="4" posy="16" group="0" rotate="0" dirx="0" diry="0" width="0" height="0" timer="0"/>
  <decoration type="f0x1" posx="5" posy="8" group="0" rotate="0" dirx="0" diry="0" width="0" height="0" timer="0"/>
  <decoration type="f0x1" posx="5" posy="19" group="0" rotate="0" dirx="0" diry="0" width="0" height="0" timer="0"/>
  <decoration type="f1x1" posx="6" posy="1" group="0" rotate="0" dirx="0" diry="0" width="0" height="0" timer="0"/>
  <decoration type="f0x3" posx="6" posy="7" group="0" rotate="0" dirx="0" diry="0" width="0" height="0" timer="0"/>
  <decoration type="f1x1" posx="6" posy="12" group="0" rotate="0" dirx="0" diry="0" width="0" height="0" timer="0"/>
  <decoration type="f0x3" posx="6" posy="18" group="0" rotate="0" dirx="0" diry="0" width="0" height="0" timer="0"/>
  <decoration type="f1x0" posx="7" posy="9" group="0" rotate="0" dirx="0" diry="0" width="0" height="0" timer="0"/>
  <decoration type="f1x0" posx="7" posy="20" group="0" rotate="0" dirx="0" diry="0" width="0" height="0" timer="0"/>
  <decoration type="f0x2" posx="9" posy="4" group="0" rotate="0" dirx="0" diry="0" width="0" height="0" timer="0"/>
  <decoration type="f0x2" posx="9" posy="15" group="0" rotate="0" dirx="0" diry="0" width="0" height="0" timer="0"/>
  <decoration type="f1x2" posx="11" posy="1" group="0" rotate="0" dirx="0" diry="0" width="0" height="0" timer="0"/>
  <decoration type="f0x0" posx="11" posy="6" group="0" rotate="0" dirx="0" diry="0" width="0" height="0" timer="0"/>
  <decoration type="f1x2" posx="11" posy="12" group="0" rotate="0" dirx="0" diry="0" width="0" height="0" timer="0"/>
  <decoration type="f0x0" posx="11" posy="17" group="0" rotate="0" dirx="0" diry="0" width="0" height="0" timer="0"/>
  <door type="door c" posx="2" posy="5" group="0" rotate="0" dirx="0" diry="0" width="0" height="0" timer="0"/>
  <door type="door b" posx="2" posy="16" group="0" rotate="0" dirx="0" diry="0" width="0" height="0" timer="0"/>
  <door type="door c" posx="10" posy="5" group="0" rotate="0" dirx="0" diry="0" width="0" height="0" timer="0"/>
  <door type="door b" posx="10" posy="16" group="0" rotate="0" dirx="0" diry="0" width="0" height="0" timer="0"/>
  <item type="coin a" posx="1" posy="5" group="0" rotate="0" dirx="0" diry="0" width="0" height="0" timer="0"/>
  <item type="coin a" posx="1" posy="16" group="0" rotate="0" dirx="0" diry="0" width="0" height="0" timer="0"/>
  <item type="coin a" posx="3" posy="1" group="0" rotate="0" dirx="0" diry="0" width="0" height="0" timer="0"/>
  <item type="coin a" posx="3" posy="20" group="0" rotate="0" dirx="0" diry="0" width="0" height="0" timer="0"/>
  <item type="coin a" posx="9" posy="1" group="0" rotate="0" dirx="0" diry="0" width="0" height="0" timer="0"/>
  <item type="coin a" posx="9" posy="20" group="0" rotate="0" dirx="0" diry="0" width="0" height="0" timer="0"/>
  <item type="coin a" posx="11" posy="5" group="0" rotate="0" dirx="0" diry="0" width="0" height="0" timer="0"/>
  <item type="coin a" posx="11" posy="16" group="0" rotate="0" dirx="0" diry="0" width="0" height="0" timer="0"/>
  <trap type="spike c" posx="2" posy="2" group="0" rotate="0" dirx="0" diry="0" width="0" height="0" timer="0"/>
  <trap type="spike b" posx="2" posy="8" group="0" rotate="0" dirx="0" diry="0" width="0" height="0" timer="0"/>
  <trap type="spike b" posx="2" posy="13" group="0" rotate="0" dirx="0" diry="0" width="0" height="0" timer="0"/>
  <trap type="spike d" posx="2" posy="19" group="0" rotate="0" dirx="0" diry="0" width="0" height="0" timer="0"/>
  <trap type="spike b" posx="3" posy="3" group="0" rotate="0" dirx="0" diry="0" width="0" height="0" timer="0"/>
  <trap type="spike c" posx="3" posy="7" group="0" rotate="0" dirx="0" diry="0" width="0" height="0" timer="0"/>
  <trap type="spike b" posx="3" posy="14" group="0" rotate="0" dirx="0" diry="0" width="0" height="0" timer="0"/>
  <trap type="spike b" posx="3" posy="18" group="0" rotate="0" dirx="0" diry="0" width="0" height="0" timer="0"/>
  <trap type="spike b" posx="4" posy="2" group="0" rotate="0" dirx="0" diry="0" width="0" height="0" timer="0"/>
  <trap type="spike b" posx="4" posy="8" group="0" rotate="0" dirx="0" diry="0" width="0" height="0" timer="0"/>
  <trap type="spike d" posx="4" posy="13" group="0" rotate="0" dirx="0" diry="0" width="0" height="0" timer="0"/>
  <trap type="spike d" posx="4" posy="19" group="0" rotate="0" dirx="0" diry="0" width="0" height="0" timer="0"/>
  <trap type="spike c" posx="5" posy="4" group="0" rotate="0" dirx="0" diry="0" width="0" height="0" timer="0"/>
  <trap type="spike b" posx="5" posy="6" group="0" rotate="0" dirx="0" diry="0" width="0" height="0" timer="0"/>
  <trap type="spike d" posx="5" posy="15" group="0" rotate="0" dirx="0" diry="0" width="0" height="0" timer="0"/>
  <trap type="spike b" posx="5" posy="17" group="0" rotate="0" dirx="0" diry="0" width="0" height="0" timer="0"/>
  <trap type="spike b" posx="7" posy="4" group="0" rotate="0" dirx="0" diry="0" width="0" height="0" timer="0"/>
  <trap type="spike c" posx="7" posy="6" group="0" rotate="0" dirx="0" diry="0" width="0" height="0" timer="0"/>
  <trap type="spike b" posx="7" posy="15" group="0" rotate="0" dirx="0" diry="0" width="0" height="0" timer="0"/>
  <trap type="spike d" posx="7" posy="17" group="0" rotate="0" dirx="0" diry="0" width="0" height="0" timer="0"/>
  <trap type="spike c" posx="8" posy="2" group="0" rotate="0" dirx="0" diry="0" width="0" height="0" timer="0"/>
  <trap type="spike c" posx="8" posy="8" group="0" rotate="0" dirx="0" diry="0" width="0" height="0" timer="0"/>
  <trap type="spike b" posx="8" posy="13" group="0" rotate="0" dirx="0" diry="0" width="0" height="0" timer="0"/>
  <trap type="spike b" posx="8" posy="19" group="0" rotate="0" dirx="0" diry="0" width="0" height="0" timer="0"/>
  <trap type="spike b" posx="9" posy="3" group="0" rotate="0" dirx="0" diry="0" width="0" height="0" timer="0"/>
  <trap type="spike b" posx="9" posy="7" group="0" rotate="0" dirx="0" diry="0" width="0" height="0" timer="0"/>
  <trap type="spike d" posx="9" posy="14" group="0" rotate="0" dirx="0" diry="0" width="0" height="0" timer="0"/>
  <trap type="spike b" posx="9" posy="18" group="0" rotate="0" dirx="0" diry="0" width="0" height="0" timer="0"/>
  <trap type="spike c" posx="10" posy="2" group="0" rotate="0" dirx="0" diry="0" width="0" height="0" timer="0"/>
  <trap type="spike b" posx="10" posy="8" group="0" rotate="0" dirx="0" diry="0" width="0" height="0" timer="0"/>
  <trap type="spike b" posx="10" posy="13" group="0" rotate="0" dirx="0" diry="0" width="0" height="0" timer="0"/>
  <trap type="spike d" posx="10" posy="19" group="0" rotate="0" dirx="0" diry="0" width="0" height="0" timer="0"/>
</level>