{"frames": {

"button_close_shadow.png":
{
	"frame": {"x":162,"y":1548,"w":104,"h":104},
	"rotated": false,
	"trimmed": false,
	"spriteSourceSize": {"x":0,"y":0,"w":104,"h":104},
	"sourceSize": {"w":104,"h":104},
	"pivot": {"x":0.5,"y":0.5}
},
"button_right.png":
{
	"frame": {"x":162,"y":1656,"w":104,"h":104},
	"rotated": false,
	"trimmed": false,
	"spriteSourceSize": {"x":0,"y":0,"w":104,"h":104},
	"sourceSize": {"w":104,"h":104},
	"pivot": {"x":0.5,"y":0.5}
},
"button_right_shadow.png":
{
	"frame": {"x":162,"y":1548,"w":104,"h":104},
	"rotated": false,
	"trimmed": false,
	"spriteSourceSize": {"x":0,"y":0,"w":104,"h":104},
	"sourceSize": {"w":104,"h":104},
	"pivot": {"x":0.5,"y":0.5}
},
"button_tick.png":
{
	"frame": {"x":4,"y":1548,"w":154,"h":154},
	"rotated": false,
	"trimmed": true,
	"spriteSourceSize": {"x":0,"y":0,"w":154,"h":154},
	"sourceSize": {"w":153,"h":153},
	"pivot": {"x":0.5,"y":0.5}
},
"button_tick_shadow.png":
{
	"frame": {"x":4,"y":1706,"w":154,"h":154},
	"rotated": false,
	"trimmed": true,
	"spriteSourceSize": {"x":0,"y":0,"w":154,"h":154},
	"sourceSize": {"w":153,"h":153},
	"pivot": {"x":0.5,"y":0.5}
},
"feed_back_bar.png":
{
	"frame": {"x":4,"y":1864,"w":680,"h":104},
	"rotated": false,
	"trimmed": true,
	"spriteSourceSize": {"x":0,"y":0,"w":680,"h":104},
	"sourceSize": {"w":679,"h":103},
	"pivot": {"x":0.5,"y":0.5}
},
"splash_racket_rocket.png":
{
	"frame": {"x":4,"y":4,"w":1366,"h":768},
	"rotated": false,
	"trimmed": false,
	"spriteSourceSize": {"x":0,"y":0,"w":1366,"h":768},
	"sourceSize": {"w":1366,"h":768},
	"pivot": {"x":0.5,"y":0.5}
},
"ui_background_0.png":
{
	"frame": {"x":4,"y":776,"w":688,"h":768},
	"rotated": false,
	"trimmed": true,
	"spriteSourceSize": {"x":0,"y":0,"w":688,"h":768},
	"sourceSize": {"w":1366,"h":768},
	"pivot": {"x":0.5,"y":0.5}
}},
"meta": {
	"app": "https://www.codeandweb.com/texturepacker",
	"version": "1.0",
	"image": "ui_atlas_1_@2x.png",
	"format": "RGBA8888",
	"size": {"w":2048,"h":2048},
	"scale": "0.5",
	"smartupdate": "$TexturePacker:SmartUpdate:d3a10391caa61269e376c89a1482205a:eeb965d62b007c71056b48d7dee0382c:2df033bb7cd4a671cb558c8e022d629c$"
}
}
